discord_logger_plus/__init__.py
discord_logger_plus/config.py
discord_logger_plus/handlers.py
discord_logger_plus/logger.py
discord_logger_plus/templates.py
discord_logger_plus/utils.py
discord_logger_plus-0.1.0.dist-info/licenses/LICENSE
discord_logger_plus-0.1.0.dist-info/METADATA
discord_logger_plus-0.1.0.dist-info/WHEEL
discord_logger_plus-0.1.0.dist-info/top_level.txt
discord_logger_plus-0.1.0.dist-info/RECORD
