Metadata-Version: 2.4
Name: discord_logger_plus
Version: 0.1.0
Summary: A smarter logger library with discord webhook and supabase
Home-page: https://github.com/mjasano/discord_logger_plus
Author: Masaru Jasano
Author-email: me@mjasano.com
Project-URL: Bug Reports, https://github.com/mjasano/discord_logger_plus/issues
Project-URL: Source, https://github.com/mjasano/discord_logger_plus
Classifier: Development Status :: 4 - Beta
Classifier: Intended Audience :: Developers
Classifier: License :: OSI Approved :: MIT License
Classifier: Operating System :: OS Independent
Classifier: Programming Language :: Python :: 3
Classifier: Programming Language :: Python :: 3.7
Classifier: Programming Language :: Python :: 3.8
Classifier: Programming Language :: Python :: 3.9
Classifier: Programming Language :: Python :: 3.10
Classifier: Topic :: Software Development :: Libraries :: Python Modules
Requires-Python: >=3.7
License-File: LICENSE
Requires-Dist: requests>=2.25.1
Requires-Dist: supabase>=1.0.3
Requires-Dist: python-dotenv>=0.19.0
Dynamic: author
Dynamic: author-email
Dynamic: classifier
Dynamic: description
Dynamic: description-content-type
Dynamic: home-page
Dynamic: license-file
Dynamic: project-url
Dynamic: requires-dist
Dynamic: requires-python
Dynamic: summary
